ositah/__init__.py
ositah/app.py
ositah/main.py
ositah/ositah.example.cfg
ositah/apps/__init__.py
ositah/apps/analysis.py
ositah/apps/export.py
ositah/apps/configuration/__init__.py
ositah/apps/configuration/callbacks.py
ositah/apps/configuration/main.py
ositah/apps/configuration/parameters.py
ositah/apps/configuration/tools.py
ositah/apps/validation/__init__.py
ositah/apps/validation/callbacks.py
ositah/apps/validation/main.py
ositah/apps/validation/parameters.py
ositah/apps/validation/tables.py
ositah/apps/validation/tools.py
ositah/assets/arrow_down_up.svg
ositah/assets/ositah.css
ositah/assets/sort_ascending.svg
ositah/assets/sort_descending.svg
ositah/assets/sorttable.js
ositah/static/style.css
ositah/templates/base.html
ositah/templates/bootstrap_login.html
ositah/templates/login_form.html
ositah/utils/__init__.py
ositah/utils/agents.py
ositah/utils/authentication.py
ositah/utils/cache.py
ositah/utils/core.py
ositah/utils/exceptions.py
ositah/utils/hito_db.py
ositah/utils/hito_db_model.py
ositah/utils/menus.py
ositah/utils/period.py
ositah/utils/projects.py
ositah/utils/teams.py
ositah/utils/utils.py
ositah-24.12.dist-info/LICENSE
ositah-24.12.dist-info/METADATA
ositah-24.12.dist-info/WHEEL
ositah-24.12.dist-info/entry_points.txt
ositah-24.12.dist-info/top_level.txt
ositah-24.12.dist-info/RECORD
