Metadata-Version: 2.1
Name: ositah
Version: 24.12
Summary: Outils de Suivi d'Activités basé sur Hito
Author-email: Michel Jouvin <michel.jouvin@ijclab.in2p3.fr>
License: BSD 3-Clause License
Project-URL: Homepage, https://gitlab.in2p3.fr/hito/ositah
Project-URL: Bug Tracker, https://gitlab.in2p3.fr/hito/ositah/-/issues
Classifier: License :: OSI Approved :: MIT License
Classifier: Operating System :: OS Independent
Classifier: Programming Language :: Python :: 3
Requires-Python: >=3.9
License-File: LICENSE
Requires-Dist: blinker
Requires-Dist: dash>=2.17
Requires-Dist: dash-bootstrap-components
Requires-Dist: flask
Requires-Dist: flask-multipass
Requires-Dist: flask-sqlalchemy~=3.0
Requires-Dist: flask-wtf
Requires-Dist: hito-tools>=24.8.1
Requires-Dist: pandas>=2.2
Requires-Dist: pymysql
Requires-Dist: python-ldap
Requires-Dist: pyyaml
Requires-Dist: simplejson
Requires-Dist: sqlalchemy~=2.0
